{
  "id": 14872,
  "url": "https://www.president.gov.tw/NEWS/14872",
  "date_roc": "99年11月16日",
  "date": "2010-11-16",
  "title": "總統偕同副總統接見我國出席「2010年APEC經濟領袖會議」代表團成員",
  "subtitle": "",
  "content": "馬英九總統今天上午偕同蕭萬長副總統在總統府接見我國出席「2010年APEC經濟領袖會議」代表團成員，對代表團此次參與APEC會議的成果與辛勞，表達肯定與感謝。總統表示，本屆APEC主題「變革與行動」 （Change and Action）非常切合亞太與全球發展趨勢，討論議題兼具「從全人類角度思考」與「需要全世界合作」兩項特色，包括氣候變遷、新流感防治及反恐等。此外，會議對APEC自由貿易區著墨頗多，領袖代表連戰在記者會上就「泛太平洋戰略經濟夥伴關係協定」（TPP）議題也有明確回應。總統推崇連領袖代表在過程中發揮卓越的外交才華，而代表團中的民間企業代表是台灣最有活力的一環，也讓與會各國對台灣留下深刻印象；總統並期許相關部會繼續努力，從參與區域合作會議中汲取經驗，取得新資訊並爭取合作機會，讓台灣在亞太地區有更寬廣的發展空間。連領袖代表則表示，代表團除參與會議獲致相當成果外，也與許多經濟體進行會談與討論，對深化雙邊實質關係極有助益。連領袖代表說，我國此次參與APEC貿易自由化第一回合檢視，表現亮麗，尤其經貿自由化與開放的程度，備受肯定；主辦會員體日本所提出的成長議題，涵蓋範圍極廣，包括縮短數位差距、輔導中小企業、天然災害防治等，台灣不僅名列前茅，更提供其他會員體許多協助。稍後，代表團一行在總統府舉行返國記者會，由連領袖代表說明此行與會的經過與成果，並接受記者提問。連領袖代表致詞時表示，「第18屆亞太經濟合作會議」圓滿落幕，我代表團除出席領袖會議、部長會議、資深官員會議，也與各國企業領袖對談交流，並進行若干雙邊會談。連領袖代表指出，本屆會議主題包括：檢視自由化趨勢下開放政策的成果、後金融危機時代，亞太區域經濟體的成長策略、檢討世界貿易組織（WTO）下杜哈回合的成效，以及目前全球天然災害與糧食供應安全等議題；我代表團於各層級會議（領袖會議、部長會議及資深官員會議）均積極參與並提出具體意見，獲得其他代表團歡迎與尊重。代表團成員包括：領袖代表連戰、領袖代表顧問財政部李述德部長、經濟部施顏祥部長、總統府國策顧問陳錫蕃大使、「兩岸和平發展基金會」張昌邦執行長、華南銀行林明成董事長、統一企業集團林蒼生總裁、中央研究院經濟所彭信坤所長、台灣大學經濟系王泓仁主任；APEC企業諮詢委員會（ABAC）代表：神通集團苗豐強董事長、威盛電子王雪紅董事長，以及國家安全會議董國猷諮詢委員、行政院新聞局江啟臣局長等人，上午由外交部長楊進添陪同，前來總統府晉見總統及副總統，國家安全會議秘書長胡為真也在座。",
  "content_paragraphs": [
    "馬英九總統今天上午偕同蕭萬長副總統在總統府接見我國出席「2010年APEC經濟領袖會議」代表團成員，對代表團此次參與APEC會議的成果與辛勞，表達肯定與感謝。總統表示，本屆APEC主題「變革與行動」 （Change and Action）非常切合亞太與全球發展趨勢，討論議題兼具「從全人類角度思考」與「需要全世界合作」兩項特色，包括氣候變遷、新流感防治及反恐等。此外，會議對APEC自由貿易區著墨頗多，領袖代表連戰在記者會上就「泛太平洋戰略經濟夥伴關係協定」（TPP）議題也有明確回應。總統推崇連領袖代表在過程中發揮卓越的外交才華，而代表團中的民間企業代表是台灣最有活力的一環，也讓與會各國對台灣留下深刻印象；總統並期許相關部會繼續努力，從參與區域合作會議中汲取經驗，取得新資訊並爭取合作機會，讓台灣在亞太地區有更寬廣的發展空間。連領袖代表則表示，代表團除參與會議獲致相當成果外，也與許多經濟體進行會談與討論，對深化雙邊實質關係極有助益。連領袖代表說，我國此次參與APEC貿易自由化第一回合檢視，表現亮麗，尤其經貿自由化與開放的程度，備受肯定；主辦會員體日本所提出的成長議題，涵蓋範圍極廣，包括縮短數位差距、輔導中小企業、天然災害防治等，台灣不僅名列前茅，更提供其他會員體許多協助。稍後，代表團一行在總統府舉行返國記者會，由連領袖代表說明此行與會的經過與成果，並接受記者提問。連領袖代表致詞時表示，「第18屆亞太經濟合作會議」圓滿落幕，我代表團除出席領袖會議、部長會議、資深官員會議，也與各國企業領袖對談交流，並進行若干雙邊會談。連領袖代表指出，本屆會議主題包括：檢視自由化趨勢下開放政策的成果、後金融危機時代，亞太區域經濟體的成長策略、檢討世界貿易組織（WTO）下杜哈回合的成效，以及目前全球天然災害與糧食供應安全等議題；我代表團於各層級會議（領袖會議、部長會議及資深官員會議）均積極參與並提出具體意見，獲得其他代表團歡迎與尊重。代表團成員包括：領袖代表連戰、領袖代表顧問財政部李述德部長、經濟部施顏祥部長、總統府國策顧問陳錫蕃大使、「兩岸和平發展基金會」張昌邦執行長、華南銀行林明成董事長、統一企業集團林蒼生總裁、中央研究院經濟所彭信坤所長、台灣大學經濟系王泓仁主任；APEC企業諮詢委員會（ABAC）代表：神通集團苗豐強董事長、威盛電子王雪紅董事長，以及國家安全會議董國猷諮詢委員、行政院新聞局江啟臣局長等人，上午由外交部長楊進添陪同，前來總統府晉見總統及副總統，國家安全會議秘書長胡為真也在座。"
  ],
  "images": [
    "https://www.president.gov.tw/img/Image/19508088-7531-4365-a729-4afc6490d7d0.jpeg",
    "https://www.president.gov.tw/img/Image/13dbc905-d8a4-4ede-b70e-f677d7b8de1d.jpeg",
    "https://www.president.gov.tw/img/Image/c70a3dad-8cfc-4c1f-a51a-27c2b41bdbec.jpeg",
    "https://www.president.gov.tw/img/Image/2557b62e-31a9-4269-8369-8517a0f2f63d.jpeg",
    "https://www.president.gov.tw/img/Image/5fca786b-052f-4126-aec3-918d6fb545fe.jpeg"
  ],
  "english_url": ""
}