{
  "id": 23191,
  "url": "https://www.president.gov.tw/NEWS/23191",
  "date_roc": "107年03月14日",
  "date": "2018-03-14",
  "title": "接見北歐退休基金投資再生能源計畫代表團　副總統：綠能產業不僅是創新推手，也能創造就業機會",
  "subtitle": "副總統接見北歐退休基金投資再生能源計畫代表團",
  "content": "陳建仁副總統今（14）日下午接見北歐退休基金投資再生能源計畫代表團，強調政府致力實現2025年非核家園目標，臺灣正全力發展再生能源，期盼與訪團建立長期互利的夥伴關係，共創「綠色」未來。\n\n副總統以英文致詞表示，北歐退休基金投資再生能源計畫代表團是臺灣重要的合作夥伴，協助我國能源產業轉型並實現未來的能源目標。\n\n副總統指出，代表團明天將赴臺中參加「臺歐風電產業國際高峰會」，他說，我國政府致力實現2025年非核家園目標，此目標將對我國的經濟、環境、國家安全及生活品質產生影響。\n\n副總統認為，在化石燃料供應量減少的情況下，特別是對像臺灣這樣的島嶼經濟而言，能源自主即成為重要的策略目標。隨著全球暖化日益嚴重，臺灣身為國際社會的一員，必須採取負責任的行動，減少我們的碳足跡。因此，臺灣正全力發展再生能源。\n\n副總統強調，總統引領臺灣前進，而行政院暨所屬部會、立法院及地方政府均給予全力支持。臺灣的產業部門及學界如中國鋼鐵公司、臺灣國際造船公司及建國科技大學等也參與其中。\n\n副總統說，政府的作為已獲得廣大的民意支持。代表團可以從中了解臺灣各界對再生能源所做的努力，而政府也正積極建構發展再生能源所需的基礎建設和投資環境。\n\n副總統也提到，政府推動發展的再生能源與目前正全方位發展的能源產業自由化、產業轉型、基礎建設完善等其他重大政策之間息息相關。他強調，上述議題攸關臺灣未來的經濟發展和國際競爭力。「綠能產業不僅是創新的推手，也能夠創造更多的就業機會。」\n\n副總統說，丹麥自1973年以來在綠能產業的非凡成就令臺灣印象深刻，他對丹麥的技術經驗和財政專業表達敬佩之意。他很高興代表團明天能夠參加高峰會，希望他們能藉此了解臺灣對發展再生能源產業的用心。\n\n副總統最後強調，臺灣政府、企業界和學術界共同投入，致力實現長期目標。代表團的合作對臺灣非常重要，期待與他們建立長期互利的夥伴關係，共創「綠色」未來。\n\n訪賓一行包括丹麥商務辦事處處長倪安升(Nicholas Enersen)、丹麥退休基金執行長裴德森(Torben Möger Pedersen)、丹麥國家出口信貸執行長伊柏安(Anette Eberhard)及哥本哈根基礎建設基金臺灣區計畫董事長艾卓儒(Anders Eldrup)等人，由外交部次長吳志中、經濟部次長龔明鑫陪同，前來總統府拜會副總統。",
  "content_paragraphs": [
    "陳建仁副總統今（14）日下午接見北歐退休基金投資再生能源計畫代表團，強調政府致力實現2025年非核家園目標，臺灣正全力發展再生能源，期盼與訪團建立長期互利的夥伴關係，共創「綠色」未來。",
    "副總統以英文致詞表示，北歐退休基金投資再生能源計畫代表團是臺灣重要的合作夥伴，協助我國能源產業轉型並實現未來的能源目標。",
    "副總統指出，代表團明天將赴臺中參加「臺歐風電產業國際高峰會」，他說，我國政府致力實現2025年非核家園目標，此目標將對我國的經濟、環境、國家安全及生活品質產生影響。",
    "副總統認為，在化石燃料供應量減少的情況下，特別是對像臺灣這樣的島嶼經濟而言，能源自主即成為重要的策略目標。隨著全球暖化日益嚴重，臺灣身為國際社會的一員，必須採取負責任的行動，減少我們的碳足跡。因此，臺灣正全力發展再生能源。",
    "副總統強調，總統引領臺灣前進，而行政院暨所屬部會、立法院及地方政府均給予全力支持。臺灣的產業部門及學界如中國鋼鐵公司、臺灣國際造船公司及建國科技大學等也參與其中。",
    "副總統說，政府的作為已獲得廣大的民意支持。代表團可以從中了解臺灣各界對再生能源所做的努力，而政府也正積極建構發展再生能源所需的基礎建設和投資環境。",
    "副總統也提到，政府推動發展的再生能源與目前正全方位發展的能源產業自由化、產業轉型、基礎建設完善等其他重大政策之間息息相關。他強調，上述議題攸關臺灣未來的經濟發展和國際競爭力。「綠能產業不僅是創新的推手，也能夠創造更多的就業機會。」",
    "副總統說，丹麥自1973年以來在綠能產業的非凡成就令臺灣印象深刻，他對丹麥的技術經驗和財政專業表達敬佩之意。他很高興代表團明天能夠參加高峰會，希望他們能藉此了解臺灣對發展再生能源產業的用心。",
    "副總統最後強調，臺灣政府、企業界和學術界共同投入，致力實現長期目標。代表團的合作對臺灣非常重要，期待與他們建立長期互利的夥伴關係，共創「綠色」未來。",
    "訪賓一行包括丹麥商務辦事處處長倪安升(Nicholas Enersen)、丹麥退休基金執行長裴德森(Torben Möger Pedersen)、丹麥國家出口信貸執行長伊柏安(Anette Eberhard)及哥本哈根基礎建設基金臺灣區計畫董事長艾卓儒(Anders Eldrup)等人，由外交部次長吳志中、經濟部次長龔明鑫陪同，前來總統府拜會副總統。"
  ],
  "images": [
    "https://www.president.gov.tw/img/Image/a1174924-cbd7-4303-b838-56b92ec980e6.jpg",
    "https://www.president.gov.tw/img/Image/0dd82242-bc7d-43b9-b38b-c8410f821b87.jpg",
    "https://www.president.gov.tw/img/Image/7ce9cd24-392b-408d-9bdb-666ae27a0503.jpg"
  ],
  "english_url": "https://english.president.gov.tw/NEWS/7032"
}