{
  "id": 11907,
  "url": "https://www.president.gov.tw/NEWS/11907",
  "date_roc": "96年12月18日",
  "date": "2007-12-18",
  "title": "總統偕同副總統主持「劍龍級潛艦成軍20周年」慶祝大會",
  "subtitle": "",
  "content": "陳總統水扁偕同呂副總統秀蓮女士今天上午在海軍左營軍區主持「劍龍級潛艦成軍20周年」慶祝大會，除親自校閱部隊並致詞。總統對於美國政府及布希總統，基於「台灣關係法」的規定與要求及對台海安全與和平的考量，同意出售八艘柴油動力潛艦給台灣，再次代表我國政府和台灣人民向美方表示由衷的感謝。總統也期許表示，相關的經費預算也已獲得立法院的支持，希望國防部和海軍能稟持著過去「劍龍級潛艦」籌建時堅忍不拔、刻苦犯難的精神，積極加速相關作業的推動。總統致詞內容全文為：今天本人非常高興能在呂副總統陪同下再度來到海軍左營基地，共同慶祝「劍龍級潛艦成軍20周年」。大家都知道，「劍龍級潛艦」是由荷蘭W.F.造船廠建造，分別於1987與1988年返抵國門，於海軍左營基地成軍後正式命名為「海龍軍艦」及「海虎軍艦」。回顧當年從簽約、興建及官兵遠赴荷蘭接艦、訓練，直到返國成軍，其中的艱辛苦楚是外界難以想像與體會的。尤其對岸的中國處心積慮，甚至以降低與荷蘭的外交關係來要脅，極力打壓、阻撓相關的軍購案，而承攬造艦的荷蘭造船廠也不時傳出財務困難，多次面臨倒閉和關廠的危機，但在大家的共同努力下，終能克服萬難，依照既定的時程完成接艦任務。「海龍」、「海虎」軍艦返國後，隨即展開成軍訓練，並且在最短時間內完成戰備，加入海軍戰鬥序列，擔負起海軍各項重大演訓及戰備任務，大幅提升了水下作戰能力，使海軍三度空間的戰力從此邁向另另外新的里程。這一段歷史非常清楚的告訴我們，很多東西即使有再多的錢也買不到，大家一定要好好珍惜。尤其像潛艦這種具有高度隱匿性與強大戰力的武器系統，取得更為不易。對於美國政府及布希總統，基於「台灣關係法」的規定與要求及對台海安全與和平的考量，同意出售八艘柴油動力潛艦給台灣，除了要再次代表我國政府和台灣人民向美方表示由衷的感謝外，相關的經費預算也已獲得立法院的支持，希望國防部和海軍能稟持著過去「劍龍級潛艦」籌建時堅忍不拔、刻苦犯難的精神，積極加速相關作業的推動。台灣四面環海，生存發展的命脈全仰賴對外經貿及航運的暢通，一旦對岸中國對我實施海上封鎖，國內的民生經濟必然也會遭受重大的衝擊與影響。因此，鞏固海疆安全與建立可恃的海上武力，才是確保台海區域穩定與健全國內經貿發展安全的保障。同時，台灣也位處東南亞到東北亞的中心樞紐位置，戰略地位極為重要，台海的安全與和平是整個亞太地區繁榮與安定的基石。因此，如何建構一支堅實的海上戰力，積極強化自我防衛能力，有效的預防戰爭、避免戰爭，不但攸關台灣的國家安全，更是捍衛亞太地區和平與穩定所應肩負的國際責任。今天我們在此慶祝劍龍級潛艦成軍20周年，除了緬懷感謝前人戮力的付出與奉獻，也特別期許大家，要體認肩膀上正擔負著無可旁貸的重責大任，以「同舟共濟、奮勇向前」的團結精神，在建軍備戰上秉持永續經營的理念，務實求精、全力以赴，以更前瞻的思維、宏觀的視野和精實的訓練，將海軍淬煉成一支現代化的鋼鐵勁旅，迎接一切挑戰。最後，再次敬祝各位嘉賓及全體官兵同仁，身體健康、萬事如意，國防建設勝利成功。",
  "content_paragraphs": [
    "陳總統水扁偕同呂副總統秀蓮女士今天上午在海軍左營軍區主持「劍龍級潛艦成軍20周年」慶祝大會，除親自校閱部隊並致詞。總統對於美國政府及布希總統，基於「台灣關係法」的規定與要求及對台海安全與和平的考量，同意出售八艘柴油動力潛艦給台灣，再次代表我國政府和台灣人民向美方表示由衷的感謝。總統也期許表示，相關的經費預算也已獲得立法院的支持，希望國防部和海軍能稟持著過去「劍龍級潛艦」籌建時堅忍不拔、刻苦犯難的精神，積極加速相關作業的推動。總統致詞內容全文為：今天本人非常高興能在呂副總統陪同下再度來到海軍左營基地，共同慶祝「劍龍級潛艦成軍20周年」。大家都知道，「劍龍級潛艦」是由荷蘭W.F.造船廠建造，分別於1987與1988年返抵國門，於海軍左營基地成軍後正式命名為「海龍軍艦」及「海虎軍艦」。回顧當年從簽約、興建及官兵遠赴荷蘭接艦、訓練，直到返國成軍，其中的艱辛苦楚是外界難以想像與體會的。尤其對岸的中國處心積慮，甚至以降低與荷蘭的外交關係來要脅，極力打壓、阻撓相關的軍購案，而承攬造艦的荷蘭造船廠也不時傳出財務困難，多次面臨倒閉和關廠的危機，但在大家的共同努力下，終能克服萬難，依照既定的時程完成接艦任務。「海龍」、「海虎」軍艦返國後，隨即展開成軍訓練，並且在最短時間內完成戰備，加入海軍戰鬥序列，擔負起海軍各項重大演訓及戰備任務，大幅提升了水下作戰能力，使海軍三度空間的戰力從此邁向另另外新的里程。這一段歷史非常清楚的告訴我們，很多東西即使有再多的錢也買不到，大家一定要好好珍惜。尤其像潛艦這種具有高度隱匿性與強大戰力的武器系統，取得更為不易。對於美國政府及布希總統，基於「台灣關係法」的規定與要求及對台海安全與和平的考量，同意出售八艘柴油動力潛艦給台灣，除了要再次代表我國政府和台灣人民向美方表示由衷的感謝外，相關的經費預算也已獲得立法院的支持，希望國防部和海軍能稟持著過去「劍龍級潛艦」籌建時堅忍不拔、刻苦犯難的精神，積極加速相關作業的推動。台灣四面環海，生存發展的命脈全仰賴對外經貿及航運的暢通，一旦對岸中國對我實施海上封鎖，國內的民生經濟必然也會遭受重大的衝擊與影響。因此，鞏固海疆安全與建立可恃的海上武力，才是確保台海區域穩定與健全國內經貿發展安全的保障。同時，台灣也位處東南亞到東北亞的中心樞紐位置，戰略地位極為重要，台海的安全與和平是整個亞太地區繁榮與安定的基石。因此，如何建構一支堅實的海上戰力，積極強化自我防衛能力，有效的預防戰爭、避免戰爭，不但攸關台灣的國家安全，更是捍衛亞太地區和平與穩定所應肩負的國際責任。今天我們在此慶祝劍龍級潛艦成軍20周年，除了緬懷感謝前人戮力的付出與奉獻，也特別期許大家，要體認肩膀上正擔負著無可旁貸的重責大任，以「同舟共濟、奮勇向前」的團結精神，在建軍備戰上秉持永續經營的理念，務實求精、全力以赴，以更前瞻的思維、宏觀的視野和精實的訓練，將海軍淬煉成一支現代化的鋼鐵勁旅，迎接一切挑戰。最後，再次敬祝各位嘉賓及全體官兵同仁，身體健康、萬事如意，國防建設勝利成功。"
  ],
  "images": [
    "https://www.president.gov.tw/img/Image/0ipk.jpg",
    "https://www.president.gov.tw/img/Image/0ipo.jpg",
    "https://www.president.gov.tw/img/Image/0ir0.jpg"
  ],
  "english_url": ""
}