{
  "id": 22931,
  "url": "https://www.president.gov.tw/NEWS/22931",
  "date_roc": "81年06月15日",
  "date": "1992-06-15",
  "title": "總統主持新任官員宣誓典禮",
  "subtitle": "",
  "content": "李總統登輝先生今天親臨主持五位新任政府官員的宣誓典禮。\n\n宣誓儀式是於上午十時，在總統府國父紀念月會進行，李副總統元簇先生、五院院長等中央與地方政府首長，都在場觀禮。\n\n五位新任政府官員包括立法院秘書長謝生富，國防部副部長汪多志、最高法院檢察署檢察總長陳涵、海軍總司令部總司令莊銘耀、行政院經濟建設委員會副主任委員蔡勳雄，面對國旗、國父遺像及李總統，高舉右手宣讀誓詞，誓以至誠，盡忠職守，恪遵法令，報效國家。\n\n宣誓後，五位新任首長向總統行禮致敬。儀式莊嚴隆重。",
  "content_paragraphs": [
    "李總統登輝先生今天親臨主持五位新任政府官員的宣誓典禮。",
    "宣誓儀式是於上午十時，在總統府國父紀念月會進行，李副總統元簇先生、五院院長等中央與地方政府首長，都在場觀禮。",
    "五位新任政府官員包括立法院秘書長謝生富，國防部副部長汪多志、最高法院檢察署檢察總長陳涵、海軍總司令部總司令莊銘耀、行政院經濟建設委員會副主任委員蔡勳雄，面對國旗、國父遺像及李總統，高舉右手宣讀誓詞，誓以至誠，盡忠職守，恪遵法令，報效國家。",
    "宣誓後，五位新任首長向總統行禮致敬。儀式莊嚴隆重。"
  ],
  "images": [],
  "english_url": ""
}