{
  "id": 28230,
  "url": "https://www.president.gov.tw/NEWS/28230",
  "date_roc": "113年03月05日",
  "date": "2024-03-05",
  "title": "出席考試委員審薦小組第1次會議　總統盼遴選優秀適任並符合社會期待的考委人選　為國家整體發展奠定堅實人力基礎",
  "subtitle": "總統出席「第14屆考試委員提名審薦小組」第1次會議",
  "content": "蔡英文總統今（5）日上午出席在總統府召開的「第14屆考試委員提名審薦小組」第1次會議，並頒發聘書予所有小組委員。\n\n總統致詞時表示，第13屆考試委員任期即將在今年8月底屆滿。依據憲法增修條文以及考試院組織法的規定，賴副總統就職第16任總統後，需要在5月底前提名新一屆考試委員，咨請立法院行使同意權。\n\n總統指出，為了審慎遴選第14屆考試委員人選，經過交接小組會商，決定採行提名審薦程序。因此，由她核定設置提名審薦小組，並請各位擔任審薦小組委員，協助下一任總統辦理提名。她也要感謝委員們願意鼎力協助，共同參與這項重要的憲法任務。\n\n總統強調，考試委員肩負提升公務人力素質以及健全文官體制運作的職責，更要前瞻國家未來人才的需求。因此，考試委員對於考試選才及人事制度，也都要有革新的理念，才能為國家整體發展奠定堅實的人力基礎，相信這也是國人對考試委員的深切期待。\n\n總統表示，各位委員都是歷練豐富的社會賢達，在座多位也曾經參與提名審薦工作，她要請大家貢獻專業和智慧，協助下一任總統，為國家遴選優秀適任並符合社會期待的考試委員人選，一起為考試院的院務發展開啟嶄新的一頁。\n\n隨後，總統頒發聘書予考試委員提名審薦小組委員，包括蕭副總統當選人美琴、考試院黃院長榮村、總統府林資政全、蕭資政新煌、和碩聯合科技股份有限公司童董事長子賢等5人。\n\n包括總統府秘書長林佳龍、副秘書長黃重諺及考試院秘書長劉建忻亦出席是項會議。",
  "content_paragraphs": [
    "蔡英文總統今（5）日上午出席在總統府召開的「第14屆考試委員提名審薦小組」第1次會議，並頒發聘書予所有小組委員。",
    "總統致詞時表示，第13屆考試委員任期即將在今年8月底屆滿。依據憲法增修條文以及考試院組織法的規定，賴副總統就職第16任總統後，需要在5月底前提名新一屆考試委員，咨請立法院行使同意權。",
    "總統指出，為了審慎遴選第14屆考試委員人選，經過交接小組會商，決定採行提名審薦程序。因此，由她核定設置提名審薦小組，並請各位擔任審薦小組委員，協助下一任總統辦理提名。她也要感謝委員們願意鼎力協助，共同參與這項重要的憲法任務。",
    "總統強調，考試委員肩負提升公務人力素質以及健全文官體制運作的職責，更要前瞻國家未來人才的需求。因此，考試委員對於考試選才及人事制度，也都要有革新的理念，才能為國家整體發展奠定堅實的人力基礎，相信這也是國人對考試委員的深切期待。",
    "總統表示，各位委員都是歷練豐富的社會賢達，在座多位也曾經參與提名審薦工作，她要請大家貢獻專業和智慧，協助下一任總統，為國家遴選優秀適任並符合社會期待的考試委員人選，一起為考試院的院務發展開啟嶄新的一頁。",
    "隨後，總統頒發聘書予考試委員提名審薦小組委員，包括蕭副總統當選人美琴、考試院黃院長榮村、總統府林資政全、蕭資政新煌、和碩聯合科技股份有限公司童董事長子賢等5人。",
    "包括總統府秘書長林佳龍、副秘書長黃重諺及考試院秘書長劉建忻亦出席是項會議。"
  ],
  "images": [
    "https://www.president.gov.tw/img/Image/f1c24378-2be7-40ac-9d19-0cb99b283630.jpg",
    "https://www.president.gov.tw/img/Image/2bbd1875-6f3c-46a1-9472-0c43c4a92ad6.jpg",
    "https://www.president.gov.tw/img/Image/2aed67d2-4416-4cbb-bc19-2c4bb3a54ec6.jpg",
    "https://www.president.gov.tw/img/Image/e3660f55-f023-403b-8447-9694c629edf7.jpg"
  ],
  "english_url": ""
}