{
  "id": 28979,
  "url": "https://www.president.gov.tw/NEWS/28979",
  "date_roc": "113年12月23日",
  "date": "2024-12-23",
  "title": "副總統感謝績優捐血人代表　盼良善力量不斷循環　讓社會更健全",
  "subtitle": "副總統接見「112年度績優捐血人代表」",
  "content": "蕭美琴副總統今（23）日上午接見「112年度績優捐血人代表」，肯定並感謝所有熱血捐血人的付出，用自身的健康來幫助其他人也獲得健康，展現臺灣的互助精神。期盼良善力量不斷循環，讓社會更好、更健全。\n\n副總統致詞時表示，很高興有機會在總統府接待全臺灣最熱血的績優捐血人代表，她要代表賴總統及政府向大家表達最高敬意，並感謝大家捐出自己的熱血，幫助其他有迫切需要的同胞。捐血人們的長期奉獻代表著臺灣的互助精神，不僅樂於幫助國內同胞，在國際上也展現「Taiwan can help」的良善力量。\n\n副總統指出，身體健康是成為績優捐血人的首要條件，大家用自身的健康來幫助其他人獲得健康，相信每個臺灣人對此都心懷感激。大家彼此幫忙，能讓社會更好、更健全。\n\n訪賓一行由台灣血液基金會董事長侯勝茂率領，衛生福利部次長周志浩陪同，前來總統府拜會副總統。",
  "content_paragraphs": [
    "蕭美琴副總統今（23）日上午接見「112年度績優捐血人代表」，肯定並感謝所有熱血捐血人的付出，用自身的健康來幫助其他人也獲得健康，展現臺灣的互助精神。期盼良善力量不斷循環，讓社會更好、更健全。",
    "副總統致詞時表示，很高興有機會在總統府接待全臺灣最熱血的績優捐血人代表，她要代表賴總統及政府向大家表達最高敬意，並感謝大家捐出自己的熱血，幫助其他有迫切需要的同胞。捐血人們的長期奉獻代表著臺灣的互助精神，不僅樂於幫助國內同胞，在國際上也展現「Taiwan can help」的良善力量。",
    "副總統指出，身體健康是成為績優捐血人的首要條件，大家用自身的健康來幫助其他人獲得健康，相信每個臺灣人對此都心懷感激。大家彼此幫忙，能讓社會更好、更健全。",
    "訪賓一行由台灣血液基金會董事長侯勝茂率領，衛生福利部次長周志浩陪同，前來總統府拜會副總統。"
  ],
  "images": [
    "https://www.president.gov.tw/img/Image/8ab21736-f894-4a5b-9ece-0ba3052a5e3d.jpg",
    "https://www.president.gov.tw/img/Image/685d8947-939c-463d-8aeb-2ebfdb327307.jpg",
    "https://www.president.gov.tw/img/Image/00abc564-13fa-440a-9c3b-06d22df9e17d.jpg",
    "https://www.president.gov.tw/img/Image/aed080fc-ed22-42a1-8f8e-6e51501f5109.jpg"
  ],
  "english_url": "https://english.president.gov.tw/NEWS/7093"
}