{
  "id": 1450,
  "url": "https://www.president.gov.tw/NEWS/1450",
  "date_roc": "91年05月17日",
  "date": "2002-05-17",
  "title": "軍禮歡送馬紹爾群島共和國總統諾特伉儷及訪問團團員",
  "subtitle": "",
  "content": "陳總統水扁先生今天代表中華民國政府與人民，以隆重軍禮歡送馬紹爾群島共和國總統諾特伉儷及訪問團團員。歡送儀式上午十一時在國家音樂廳舉行，在鳴放廿一響禮炮聲中，樂隊先後演奏中、馬兩國國歌，儀式結束後，諾特總統暨隨行團員一一向陳總統辭行，隨後，在場參加歡送儀式的中華民國政府首長及各國駐華使節，也先後向諾特總統道別。諾特總統等一行訂下午離華，結束六天的訪問行程。",
  "content_paragraphs": [
    "陳總統水扁先生今天代表中華民國政府與人民，以隆重軍禮歡送馬紹爾群島共和國總統諾特伉儷及訪問團團員。歡送儀式上午十一時在國家音樂廳舉行，在鳴放廿一響禮炮聲中，樂隊先後演奏中、馬兩國國歌，儀式結束後，諾特總統暨隨行團員一一向陳總統辭行，隨後，在場參加歡送儀式的中華民國政府首長及各國駐華使節，也先後向諾特總統道別。諾特總統等一行訂下午離華，結束六天的訪問行程。"
  ],
  "images": [],
  "english_url": ""
}