{
  "id": 1752,
  "url": "https://www.president.gov.tw/NEWS/1752",
  "date_roc": "91年02月22日",
  "date": "2002-02-22",
  "title": "副總統訪視新竹縣",
  "subtitle": "",
  "content": "呂副總統秀蓮女士今天到新竹縣各休閒農場參觀，以實地了解我國加入ＷＴＯ之後可能遭遇的困境與挑戰。副總統在聽取新竹縣長鄭永金所做的簡報後指出，我國在加入ＷＴＯ之後將開放大陸兩千項以上農產品進口，這將帶來重大的挑戰，希望各界能做好準備。副總統強調，我們不但要接受挑戰，更要克服挑戰，因為危機也就是轉機。以新竹縣為例，新竹以高科技及觀光農業著名，並兼具客家人文特色，在我國加入ＷＴＯ之後應該有更上層樓的發展。為了因應加入ＷＴＯ的衝擊，副總統進一步提出兩個構想，其中之一是：如果我國農業在面臨轉型時仍有困難無法克服，她建議可以組團帶著技術到海外邦交國集體投資闖天下，資金部分則由我國政府或邦交國政府配合解決，希望這項計畫在半年內可以順利推動。副總統不認為到大陸投資是一個理想的地方，儘管大陸與我們語言相同，但副總統強調，「如果我國加入ＷＴＯ有一分的衝擊，大陸則有十分」，同時也不能盲目地到大陸投資，因為她看到很多到大陸投資而妻離子散的不幸，這種人生意義與價值何在？值得大家深思。其次，最近國內科技業界在討論八吋晶圓到大陸投資以搶得市場先機的問題，副總統認為，八吋晶圓是我國產業的命脈，在新竹市甚至可以發展成科技聚落生活圈，如果八吋晶圓移到大陸去，此一聚落可能會面臨沒落的危機。副總統也了解此一趨勢無法阻擋，但卻沒有聽到新竹在地人士對此一問題的看法，究竟應該如何因應，副總統也提醒大家應及早籌謀因應。副總統接著表示，下週她將發起待業家庭助學基金，以協助高職以下繳不起學費或午餐費學生的困境，副總統說，教育不能有空窗期，希望全國各界善心人士一起響應這項活動。副總統今天的新竹縣行程還包括參訪六家問禮堂、新埔九芎湖休閒農場、巨埔農場、橫山內灣山城等。",
  "content_paragraphs": [
    "呂副總統秀蓮女士今天到新竹縣各休閒農場參觀，以實地了解我國加入ＷＴＯ之後可能遭遇的困境與挑戰。副總統在聽取新竹縣長鄭永金所做的簡報後指出，我國在加入ＷＴＯ之後將開放大陸兩千項以上農產品進口，這將帶來重大的挑戰，希望各界能做好準備。副總統強調，我們不但要接受挑戰，更要克服挑戰，因為危機也就是轉機。以新竹縣為例，新竹以高科技及觀光農業著名，並兼具客家人文特色，在我國加入ＷＴＯ之後應該有更上層樓的發展。為了因應加入ＷＴＯ的衝擊，副總統進一步提出兩個構想，其中之一是：如果我國農業在面臨轉型時仍有困難無法克服，她建議可以組團帶著技術到海外邦交國集體投資闖天下，資金部分則由我國政府或邦交國政府配合解決，希望這項計畫在半年內可以順利推動。副總統不認為到大陸投資是一個理想的地方，儘管大陸與我們語言相同，但副總統強調，「如果我國加入ＷＴＯ有一分的衝擊，大陸則有十分」，同時也不能盲目地到大陸投資，因為她看到很多到大陸投資而妻離子散的不幸，這種人生意義與價值何在？值得大家深思。其次，最近國內科技業界在討論八吋晶圓到大陸投資以搶得市場先機的問題，副總統認為，八吋晶圓是我國產業的命脈，在新竹市甚至可以發展成科技聚落生活圈，如果八吋晶圓移到大陸去，此一聚落可能會面臨沒落的危機。副總統也了解此一趨勢無法阻擋，但卻沒有聽到新竹在地人士對此一問題的看法，究竟應該如何因應，副總統也提醒大家應及早籌謀因應。副總統接著表示，下週她將發起待業家庭助學基金，以協助高職以下繳不起學費或午餐費學生的困境，副總統說，教育不能有空窗期，希望全國各界善心人士一起響應這項活動。副總統今天的新竹縣行程還包括參訪六家問禮堂、新埔九芎湖休閒農場、巨埔農場、橫山內灣山城等。"
  ],
  "images": [
    "https://www.president.gov.tw/img/Image/0311.jpg"
  ],
  "english_url": ""
}