{
  "id": 22471,
  "url": "https://www.president.gov.tw/NEWS/22471",
  "date_roc": "84年06月07日",
  "date": "1995-06-07",
  "title": "總統前往美國訪問",
  "subtitle": "",
  "content": "李總統登輝伉儷今天啟程前往美國訪問，行前對朝野各黨暨社會各界所表達的支持與祝福，表示深切的謝意。\n\n李總統伉儷偕同總統府秘書長吳伯雄夫婦及國家安全會議秘書長丁懋時夫婦等一行今午搭乘中華航空公司專機訪美，李副總統元簇先生、總統府資政蔣彥士夫婦、行政院院長連戰夫婦、立法院院長劉松藩夫婦、司法院院長施啟揚、監察院院長陳履安、國民大會秘書長陳金讓夫婦、執政黨中央委員會秘書長許水德夫婦、行政院部會首長、考試院考選部部長王作榮、銓敘部部長關中、監察院審計部審計長蘇振平夫婦、總統府參軍長陳廷寵夫婦、副秘書長戴瑞明夫婦、國家安全會議副秘書長鄭文華夫婦、台灣省長宋楚瑜夫婦、議長劉炳偉夫婦、台北市長陳水扁、議長陳健治夫婦、高雄市長吳敦義夫婦、議長陳田錨、駐華外交使節團團長巴拉圭駐華大使羅培茲、美國在台協會台北辦事處處長貝霖，及康乃爾大學同學會代表等七十餘人前往機場送行。\n\n為使國人瞭解總統訪美觀感，預定於本（六）月十二日總統返國時舉行記者會。",
  "content_paragraphs": [
    "李總統登輝伉儷今天啟程前往美國訪問，行前對朝野各黨暨社會各界所表達的支持與祝福，表示深切的謝意。",
    "李總統伉儷偕同總統府秘書長吳伯雄夫婦及國家安全會議秘書長丁懋時夫婦等一行今午搭乘中華航空公司專機訪美，李副總統元簇先生、總統府資政蔣彥士夫婦、行政院院長連戰夫婦、立法院院長劉松藩夫婦、司法院院長施啟揚、監察院院長陳履安、國民大會秘書長陳金讓夫婦、執政黨中央委員會秘書長許水德夫婦、行政院部會首長、考試院考選部部長王作榮、銓敘部部長關中、監察院審計部審計長蘇振平夫婦、總統府參軍長陳廷寵夫婦、副秘書長戴瑞明夫婦、國家安全會議副秘書長鄭文華夫婦、台灣省長宋楚瑜夫婦、議長劉炳偉夫婦、台北市長陳水扁、議長陳健治夫婦、高雄市長吳敦義夫婦、議長陳田錨、駐華外交使節團團長巴拉圭駐華大使羅培茲、美國在台協會台北辦事處處長貝霖，及康乃爾大學同學會代表等七十餘人前往機場送行。",
    "為使國人瞭解總統訪美觀感，預定於本（六）月十二日總統返國時舉行記者會。"
  ],
  "images": [],
  "english_url": ""
}