{
  "id": 17600,
  "url": "https://www.president.gov.tw/NEWS/17600",
  "date_roc": "102年04月17日",
  "date": "2013-04-17",
  "title": "總統出席「中華民國婦女聯合會63周年會慶晚會」",
  "subtitle": "",
  "content": "",
  "content_paragraphs": [],
  "images": [
    "https://www.president.gov.tw/img/Image/f5aeb8aa-3f89-4acc-9dca-96f62f10df05.jpeg",
    "https://www.president.gov.tw/img/Image/0873c1a9-49be-419a-9046-760af0755f54.jpeg",
    "https://www.president.gov.tw/img/Image/311afb76-73d9-4747-9f4c-edc3e5fa4b26.jpeg"
  ],
  "english_url": ""
}