{
  "id": 18228,
  "url": "https://www.president.gov.tw/NEWS/18228",
  "date_roc": "102年12月05日",
  "date": "2013-12-05",
  "title": "總統接見102年度參與監所教化及保護事業有功人士與團體代表",
  "subtitle": "",
  "content": "",
  "content_paragraphs": [],
  "images": [
    "https://www.president.gov.tw/img/Image/9a4fae9d-18dd-41b1-9df9-acedd794b86f.jpg",
    "https://www.president.gov.tw/img/Image/6c6ae907-bf24-453b-9d7b-441de241a720.jpg",
    "https://www.president.gov.tw/img/Image/6ce4acb1-746e-4037-a198-23caf45768b0.jpg"
  ],
  "english_url": ""
}