{
  "id": 19576,
  "url": "https://www.president.gov.tw/NEWS/19576",
  "date_roc": "104年06月24日",
  "date": "2015-06-24",
  "title": "總統視察外交部",
  "subtitle": "",
  "content": "",
  "content_paragraphs": [],
  "images": [
    "https://www.president.gov.tw/img/Image/5743862a-edec-4941-8f9b-433c5ddfd6d3.jpg",
    "https://www.president.gov.tw/img/Image/9199f733-a013-4d73-b0a7-36b20ae5bf0c.jpg",
    "https://www.president.gov.tw/img/Image/f51ab77a-79e6-4709-97b0-e53cd467607f.jpg"
  ],
  "english_url": ""
}