{
  "id": 19640,
  "url": "https://www.president.gov.tw/NEWS/19640",
  "date_roc": "104年07月30日",
  "date": "2015-07-30",
  "title": "總統接見「2015年西班牙－中華民國（臺灣）國會議員友好協會」訪華團",
  "subtitle": "",
  "content": "",
  "content_paragraphs": [],
  "images": [
    "https://www.president.gov.tw/img/Image/a63a1556-f3fa-476d-a3cf-f416f9471cbc.jpg",
    "https://www.president.gov.tw/img/Image/01cb4e92-d25f-48b4-9d02-41fe278d8d2b.jpg",
    "https://www.president.gov.tw/img/Image/9f73c054-3bed-455d-8cc9-c0f171b89ea2.jpg"
  ],
  "english_url": ""
}