{
  "id": 13884,
  "url": "https://www.president.gov.tw/NEWS/13884",
  "date_roc": "98年12月11日",
  "date": "2009-12-11",
  "title": "總統接見全國各區漁會理事長、常務監事及總幹事",
  "subtitle": "",
  "content": "",
  "content_paragraphs": [],
  "images": [
    "https://www.president.gov.tw/img/Image/0tml.jpg",
    "https://www.president.gov.tw/img/Image/0tmn.jpg",
    "https://www.president.gov.tw/img/Image/0tmh.jpg",
    "https://www.president.gov.tw/img/Image/0tmj.jpg",
    "https://www.president.gov.tw/img/Image/0tmp.jpg",
    "https://www.president.gov.tw/img/Image/0tmr.jpg"
  ],
  "english_url": ""
}