{
  "id": 26653,
  "url": "https://www.president.gov.tw/NEWS/26653",
  "date_roc": "111年04月02日",
  "date": "2022-04-02",
  "title": "出席2022中華職棒開幕戰　副總統以實際行動進場支持臺灣棒球",
  "subtitle": "副總統出席「2022中華職棒開幕戰」",
  "content": "賴清德副總統今（2）日晚間前往臺中洲際棒球場出席「2022中華職棒開幕戰」，以實際行動進場支持臺灣棒球，並為選手們精彩的熱血表現加油喝采。\n\n今天開幕戰由中信兄弟隊對戰統一獅隊，副總統在臺中市長盧秀燕、中華職業棒球大聯盟會長蔡其昌及秘書長楊清瓏等人陪同下，與球迷們一同在低溫的雨中觀賞賽事，為選手的精彩熱血表現加油喝采，現場氣氛相當熱烈。\n\n之後，開幕戰因雨勢過大、氣候不佳而宣布延賽，副總統一行才離場，用具體行動表達支持臺灣棒球的立場與決心。",
  "content_paragraphs": [
    "賴清德副總統今（2）日晚間前往臺中洲際棒球場出席「2022中華職棒開幕戰」，以實際行動進場支持臺灣棒球，並為選手們精彩的熱血表現加油喝采。",
    "今天開幕戰由中信兄弟隊對戰統一獅隊，副總統在臺中市長盧秀燕、中華職業棒球大聯盟會長蔡其昌及秘書長楊清瓏等人陪同下，與球迷們一同在低溫的雨中觀賞賽事，為選手的精彩熱血表現加油喝采，現場氣氛相當熱烈。",
    "之後，開幕戰因雨勢過大、氣候不佳而宣布延賽，副總統一行才離場，用具體行動表達支持臺灣棒球的立場與決心。"
  ],
  "images": [
    "https://www.president.gov.tw/img/Image/5c8eb06d-36a5-4a3c-b56c-c8a45ec4e68b.jpg",
    "https://www.president.gov.tw/img/Image/29081185-47ee-4744-be33-04bb43210708.jpg",
    "https://www.president.gov.tw/img/Image/5e82aa9e-231b-4aa3-a979-54079f04b0f2.jpg",
    "https://www.president.gov.tw/img/Image/3d50e605-2655-477a-b883-612f2a1e1d3a.jpg"
  ],
  "english_url": "https://english.president.gov.tw/NEWS/7084"
}