{
  "id": 27111,
  "url": "https://www.president.gov.tw/NEWS/27111",
  "date_roc": "111年11月06日",
  "date": "2022-11-06",
  "title": "肯定醫事放射師在疫情期間站在第一線　總統：借重放射師專業　共同提升醫療品質　促進精準醫療發展",
  "subtitle": "總統為「國際醫事放射師節慶祝大會」錄製致詞影片",
  "content": "蔡英文總統今（6）日上午以錄影方式為「國際醫事放射師節慶祝大會」致詞，感謝醫事放射師在疫情期間站在第一線，確認民眾的確診情況。並表示，隨著生物醫學影像及放射科學的日新月異，醫事放射師的角色也越來越重要，期盼未來借重放射師專業，共同提升醫療品質，並促進精準醫療的發展。\n\n總統致詞內容：\n\n11月8號是國際醫事放射師節，我要祝各位，國際放射師節快樂。感謝各位用專業守護臺灣，也守護全國民眾的健康。\n\n在疫情期間，我們所有的醫事放射師朋友都肩負重任，在疫情的第一線，透過醫學影像的取得與判讀，確認民眾確診的情況。\n\n因為長期穿著隔離衣，戴著N95口罩，汗水經常濕透整身的隔離衣，臉上也會有深深的壓痕，真的很辛苦。\n\n在防疫過程中，各位都是最關鍵的防疫英雄，我要向各位的付出，表達最深的敬意和感謝。\n\n隨著生物醫學影像，以及放射科學日新月異，醫事放射師的角色，也越來越重要。\n\n有許多的儀器，都需要放射師來操作，為民眾進行檢測及醫療，來提升診斷的準確性和時效性。對於病患的整體治療，真的有很大的貢獻。\n\n未來，我們也需要繼續借重各位放射師的專業，共同提升醫療的品質，並且促進精準醫療的發展。\n\n最後，我要祝大會活動順利，也要再次祝各位放射師節快樂，謝謝。",
  "content_paragraphs": [
    "蔡英文總統今（6）日上午以錄影方式為「國際醫事放射師節慶祝大會」致詞，感謝醫事放射師在疫情期間站在第一線，確認民眾的確診情況。並表示，隨著生物醫學影像及放射科學的日新月異，醫事放射師的角色也越來越重要，期盼未來借重放射師專業，共同提升醫療品質，並促進精準醫療的發展。",
    "總統致詞內容：",
    "11月8號是國際醫事放射師節，我要祝各位，國際放射師節快樂。感謝各位用專業守護臺灣，也守護全國民眾的健康。",
    "在疫情期間，我們所有的醫事放射師朋友都肩負重任，在疫情的第一線，透過醫學影像的取得與判讀，確認民眾確診的情況。",
    "因為長期穿著隔離衣，戴著N95口罩，汗水經常濕透整身的隔離衣，臉上也會有深深的壓痕，真的很辛苦。",
    "在防疫過程中，各位都是最關鍵的防疫英雄，我要向各位的付出，表達最深的敬意和感謝。",
    "隨著生物醫學影像，以及放射科學日新月異，醫事放射師的角色，也越來越重要。",
    "有許多的儀器，都需要放射師來操作，為民眾進行檢測及醫療，來提升診斷的準確性和時效性。對於病患的整體治療，真的有很大的貢獻。",
    "未來，我們也需要繼續借重各位放射師的專業，共同提升醫療的品質，並且促進精準醫療的發展。",
    "最後，我要祝大會活動順利，也要再次祝各位放射師節快樂，謝謝。"
  ],
  "images": [
    "https://www.president.gov.tw/img/Image/145fb0f4-0b18-4803-9890-7dc194d5daf6.jpg"
  ],
  "english_url": "https://english.president.gov.tw/NEWS/7093"
}